{
  "$schema": "https://railway.app/railway.schema.json",
  "build": {
    "builder": "NIXPACKS",
    "buildCommand": "./build-railway.sh",
    "nixpacks": {
      "providers": ["nodejs"],
      "phases": {
        "setup": {
          "nixpkgs": ["nodejs_20", "npm"]
        }
      }
    }
  },
  "deploy": {
    "startCommand": "npm run railway:start",
    "healthcheckPath": "/api/health",
    "healthcheckTimeout": 100,
    "restartPolicyType": "ON_FAILURE",
    "restartPolicyMaxRetries": 10
  }
}
